dlabx/__init__.py
dlabx/backtracking/Exist_Word.py
dlabx/backtracking/Generate_Combinations.py
dlabx/backtracking/Generate_Permutations.py
dlabx/backtracking/Generate_Power_Set.py
dlabx/backtracking/Graph_Coloring.py
dlabx/backtracking/Hamiltonian_Path.py
dlabx/backtracking/K_Coloring.py
dlabx/backtracking/Knights_Tour.py
dlabx/backtracking/Maze.py
dlabx/backtracking/N_Queens.py
dlabx/backtracking/Partition_Array.py
dlabx/backtracking/Partition_Into_K_Subsets.py
dlabx/backtracking/Subset_Sum.py
dlabx/backtracking/Sudoku.py
dlabx/backtracking/Sum_Of_Subsets.py
dlabx/backtracking/__init__.py
dlabx/bruteforce/Distance.py
dlabx/bruteforce/Generate_Permutations.py
dlabx/bruteforce/Generate_Subsets.py
dlabx/bruteforce/Knapsack_Bruteforce.py
dlabx/bruteforce/Naive_Search.py
dlabx/bruteforce/Tsp_Brute_Force.py
dlabx/bruteforce/__init__.py
dlabx/data_structure/__init__.py
dlabx/data_structure/linear_data_structure/__init__.py
dlabx/data_structure/linear_data_structure/array.py
dlabx/data_structure/linear_data_structure/linked_list.py
dlabx/data_structure/linear_data_structure/queue.py
dlabx/data_structure/linear_data_structure/single_shared_stack.py
dlabx/data_structure/linear_data_structure/stack.py
dlabx/data_structure/non_linear_data_structure/__init__.py
dlabx/data_structure/non_linear_data_structure/graph_representations.py
dlabx/data_structure/non_linear_data_structure/graphs.py
dlabx/data_structure/non_linear_data_structure/tree.py
dlabx/divide_and_conquer/Closest_Pair_Of_Points.py
dlabx/divide_and_conquer/Convex_Hull.py
dlabx/divide_and_conquer/Fft.py
dlabx/divide_and_conquer/Karatsuba.py
dlabx/divide_and_conquer/Maximum_Subarray.py
dlabx/divide_and_conquer/Strassen_Matrix_Multiplication.py
dlabx/divide_and_conquer/__init__.py
dlabx/dynamic_programming/Bell_Numbers.py
dlabx/dynamic_programming/Can_Partition.py
dlabx/dynamic_programming/Catalan_Numbers.py
dlabx/dynamic_programming/Count_Paths.py
dlabx/dynamic_programming/Edit_Distance.py
dlabx-0.1.0.dist-info/licenses/LICENCE.txt
dlabx-0.1.0.dist-info/METADATA
dlabx-0.1.0.dist-info/WHEEL
dlabx-0.1.0.dist-info/top_level.txt
dlabx-0.1.0.dist-info/RECORD
