Metadata-Version: 2.4
Name: dlabx
Version: 0.1.0
Summary: Dhruv's Lab - A Python library for algorithms and data structures
Author-email: Dhruv Sonani <dhruvsonani788@gmail.com>
License-Expression: MIT
Classifier: Programming Language :: Python :: 3
Classifier: Operating System :: OS Independent
Requires-Python: >=3.8
License-File: LICENCE.txt
Dynamic: license-file
